odoo8_addon_l10n_nl_xaf_auditfile_export-8.0.2.0.3-py2.7-nspkg.pth
odoo8_addon_l10n_nl_xaf_auditfile_export-8.0.2.0.3.dist-info/METADATA
odoo8_addon_l10n_nl_xaf_auditfile_export-8.0.2.0.3.dist-info/RECORD
odoo8_addon_l10n_nl_xaf_auditfile_export-8.0.2.0.3.dist-info/WHEEL
odoo8_addon_l10n_nl_xaf_auditfile_export-8.0.2.0.3.dist-info/namespace_packages.txt
odoo8_addon_l10n_nl_xaf_auditfile_export-8.0.2.0.3.dist-info/top_level.txt
odoo_addons/l10n_nl_xaf_auditfile_export/README.rst
odoo_addons/l10n_nl_xaf_auditfile_export/__init__.py
odoo_addons/l10n_nl_xaf_auditfile_export/__openerp__.py
odoo_addons/l10n_nl_xaf_auditfile_export/data/XmlAuditfileFinancieel3.2.xsd
odoo_addons/l10n_nl_xaf_auditfile_export/demo/res_partner.xml
odoo_addons/l10n_nl_xaf_auditfile_export/i18n/en_US.po
odoo_addons/l10n_nl_xaf_auditfile_export/i18n/l10n_nl_xaf_auditfile_export.pot
odoo_addons/l10n_nl_xaf_auditfile_export/i18n/nl.po
odoo_addons/l10n_nl_xaf_auditfile_export/models/__init__.py
odoo_addons/l10n_nl_xaf_auditfile_export/models/ir_qweb.py
odoo_addons/l10n_nl_xaf_auditfile_export/models/xaf_auditfile_export.py
odoo_addons/l10n_nl_xaf_auditfile_export/security/ir.model.access.csv
odoo_addons/l10n_nl_xaf_auditfile_export/static/description/icon.png
odoo_addons/l10n_nl_xaf_auditfile_export/tests/__init__.py
odoo_addons/l10n_nl_xaf_auditfile_export/tests/test_l10n_nl_xaf_auditfile_export.py
odoo_addons/l10n_nl_xaf_auditfile_export/views/menu.xml
odoo_addons/l10n_nl_xaf_auditfile_export/views/xaf_auditfile_export.xml
odoo_addons/l10n_nl_xaf_auditfile_export/views/xaf_template_all.xml
odoo_addons/l10n_nl_xaf_auditfile_export/views/xaf_template_default.xml
